LICENSE
MANIFEST.in
README.rst
setup.py
mp3fm/__init__.py
mp3fm/gui.py
mp3fm/mp3fm.py
mp3fm/pack.py
mp3fm/unpack.py
mp3fm/update.py
mp3fm.egg-info/PKG-INFO
mp3fm.egg-info/SOURCES.txt
mp3fm.egg-info/dependency_links.txt
mp3fm.egg-info/entry_points.txt
mp3fm.egg-info/requires.txt
mp3fm.egg-info/top_level.txt