Metadata-Version: 1.1
Name: mp3fm
Version: 1.0.4
Summary: I believe that for Music Lovers its a big problem to keep songs organized into folders, so here comes a simple solution to that problem. Just run the app and it will Pack the Songs into folders according to the option you choose from Album(Movie)/Artist/Year/Comments/Title/Duration.
Home-page: https://github.com/Aki92/mp3fm
Author: Akshit Agarwal
Author-email: akshit.jiit@gmail.com
License: MIT
Platform: UNKNOWN
Classifier: Environment :: Console
Classifier: Topic :: Multimedia
